opensarlab_profile_label/__init__.py
opensarlab_profile_label/_version.py
opensarlab_profile_label/handlers.py
opensarlab_profile_label/labextension/build_log.json
opensarlab_profile_label/labextension/package.json
opensarlab_profile_label/labextension/static/lib_index_js.0a341239aaa15ba37651.js
opensarlab_profile_label/labextension/static/lib_index_js.0a341239aaa15ba37651.js.map
opensarlab_profile_label/labextension/static/remoteEntry.39a3909d473d0f8b3973.js
opensarlab_profile_label/labextension/static/remoteEntry.39a3909d473d0f8b3973.js.map
opensarlab_profile_label/labextension/static/style.js
opensarlab_profile_label/labextension/static/style_index_js.67df8c57f7fba941e25a.js
opensarlab_profile_label/labextension/static/style_index_js.67df8c57f7fba941e25a.js.map
opensarlab_profile_label/labextension/static/vendors-node_modules_css-loader_dist_runtime_api_js-node_modules_css-loader_dist_runtime_cssW-72eba1.10b4be9b9deedd2ef288.js
opensarlab_profile_label/labextension/static/vendors-node_modules_css-loader_dist_runtime_api_js-node_modules_css-loader_dist_runtime_cssW-72eba1.10b4be9b9deedd2ef288.js.map
opensarlab_profile_label/labextension/static/vendors-node_modules_jupyterlab-topbar_lib_index_js.e22412ff5b60aa590b8d.js
opensarlab_profile_label/labextension/static/vendors-node_modules_jupyterlab-topbar_lib_index_js.e22412ff5b60aa590b8d.js.map
opensarlab_profile_label-0.1.2.data/data/etc/jupyter/jupyter_notebook_config.d/opensarlab_profile_label.json
opensarlab_profile_label-0.1.2.data/data/etc/jupyter/jupyter_server_config.d/opensarlab_profile_label.json
opensarlab_profile_label-0.1.2.data/data/share/jupyter/labextensions/opensarlab-profile-label/build_log.json
opensarlab_profile_label-0.1.2.data/data/share/jupyter/labextensions/opensarlab-profile-label/install.json
opensarlab_profile_label-0.1.2.data/data/share/jupyter/labextensions/opensarlab-profile-label/package.json
opensarlab_profile_label-0.1.2.dist-info/LICENSE
opensarlab_profile_label-0.1.2.dist-info/METADATA
opensarlab_profile_label-0.1.2.dist-info/WHEEL
opensarlab_profile_label-0.1.2.dist-info/top_level.txt
opensarlab_profile_label-0.1.2.dist-info/RECORD
