Metadata-Version: 2.1
Name: opensarlab-profile-label
Version: 0.1.2
Summary: A JupyterLab extension for OpenSARlab that provides the current profile label to the frontend.
Home-page: https://github.com/ASFOpenSARlab/opensarlab-extensions
Author: ASF OpenSARlab Team
Author-email: uaf-jupyterhub-asf@alaska.edu
License: BSD-3-Clause
Keywords: Jupyter,JupyterLab,JupyterLab3
Platform: Linux
Platform: Mac OS X
Platform: Windows
Classifier: License :: OSI Approved :: BSD License
Classifier: Programming Language :: Python
Classifier: Programming Language :: Python :: 3
Classifier: Programming Language :: Python :: 3.6
Classifier: Programming Language :: Python :: 3.7
Classifier: Programming Language :: Python :: 3.8
Classifier: Programming Language :: Python :: 3.9
Classifier: Programming Language :: Python :: 3.10
Classifier: Framework :: Jupyter
Classifier: Framework :: Jupyter :: JupyterLab
Classifier: Framework :: Jupyter :: JupyterLab :: 3
Classifier: Framework :: Jupyter :: JupyterLab :: Extensions
Classifier: Framework :: Jupyter :: JupyterLab :: Extensions :: Prebuilt
Requires-Python: >=3.8
License-File: LICENSE
Requires-Dist: jupyter-server (<2,>=1.6)
Requires-Dist: jupyterlab-topbar (~=0.6.0)
